flickr_api/__init__.py
flickr_api/_version.py
flickr_api/api.py
flickr_api/auth.py
flickr_api/cache.py
flickr_api/flickrerrors.py
flickr_api/keys.py
flickr_api/method_call.py
flickr_api/methods.py
flickr_api/multipart.py
flickr_api/objects.py
flickr_api/reflection.py
flickr_api/tools.py
flickr_api/upload.py
flickr_api_dlebech-0.6.dist-info/DESCRIPTION.rst
flickr_api_dlebech-0.6.dist-info/METADATA
flickr_api_dlebech-0.6.dist-info/RECORD
flickr_api_dlebech-0.6.dist-info/WHEEL
flickr_api_dlebech-0.6.dist-info/metadata.json
flickr_api_dlebech-0.6.dist-info/top_level.txt
