Metadata-Version: 2.0
Name: flickr-api-dlebech
Version: 0.6
Summary: Python wrapper for the Flickr API
Home-page: http://code.google.com/p/python-flickr-api/
Author: Alexis Mignon
Author-email: alexis.mignon@gmail.com
License: BSD License
Platform: UNKNOWN
Requires-Dist: oauth
